test_api_3/__init__.py
test_api_3/example.py
test_api_3/scripts.py
test_api_3/static/__init__.py
test_api_3-0.0.1.dist-info/METADATA
test_api_3-0.0.1.dist-info/WHEEL
test_api_3-0.0.1.dist-info/entry_points.txt
test_api_3-0.0.1.dist-info/top_level.txt
test_api_3-0.0.1.dist-info/RECORD
